normetapi/__init__.py
normetapi/api.py
normetapi/version.py
normetapi-0.1.0.dist-info/LICENSE
normetapi-0.1.0.dist-info/METADATA
normetapi-0.1.0.dist-info/WHEEL
normetapi-0.1.0.dist-info/top_level.txt
normetapi-0.1.0.dist-info/RECORD
