Metadata-Version: 2.1
Name: normetapi
Version: 0.1.0
Summary: A small library for interacting with the MET Norway Weather API.
Home-page: https://github.com/andersle/normetapi
Author: Anders Lervik
Author-email: andersle@gmail.com
License: MIT
Keywords: met api
Platform: UNKNOWN
Classifier: Development Status :: 3 - Alpha
Classifier: Environment :: Console
Classifier: Intended Audience :: End Users/Desktop
Classifier: License :: OSI Approved :: MIT License
Classifier: Natural Language :: English
Classifier: Operating System :: MacOS :: MacOS X
Classifier: Operating System :: POSIX
Classifier: Programming Language :: Python :: 3
Classifier: Programming Language :: Python :: 3.8
Classifier: Programming Language :: Python :: 3.9
Classifier: Topic :: Other/Nonlisted Topic
Requires-Dist: requests (>=2.22.0)
